mikes_toolbox2/__init__.py
mikes_toolbox2/my_toolbox.py
mikes_toolbox2-0.0.2.dist-info/METADATA
mikes_toolbox2-0.0.2.dist-info/WHEEL
mikes_toolbox2-0.0.2.dist-info/RECORD
